{"baseUrl":true,"coreVersion":6,"ine":"","inq":"Tab","ins":[],"mous":[{"attr":"{\"btNext\":false,\"desc\":false,\"flow\":true,\"itemtarget\":\"#播放器\",\"max\":0,\"row\":2,\"type\":5}","host":{"a":"#爬虫","v":"{\"cookie\":\"language\\u003dcn_CN\",\"mode\":0,\"pn_raise\":1,\"pn_start\":1,\"ua\":\"#PC\",\"url\":\"http://old.workgreat11.live/v.php?category\\u003d最热\\u0026viewtype\\u003dbasic\\u0026page\\u003d#PN#\"}"},"ins":[{"a":"list","s":[{"a":"list","v":".get(.listchannel)"},{"a":"name","v":".get(a img).a(title)"},{"a":"url","v":".get(a).a(href)"},{"a":"img","v":".get(a img).a(src)"},{"a":"msg","v":".c(时长:).get(div.listchannel).ty(时长:\u003c/span\u003e).tz(\u003cspan class\u003d\"info\"\u003e添加时间:\u003c/span\u003e).t().c(时间:).get(div.listchannel).ty(添加时间:\u003c/span\u003e).tz(\u003cspan class\u003d\"info\"\u003e作者:\u003c/span\u003e).t()"},{"a":"prev"},{"a":"next"},{"a":"tail"}]}],"ors":[{"a":"screen","v":"最热+当前最热\u003dhot+本月最热\u003dtop+上月最热\u003dtop\u0026m\u003d-1"}],"sign":"最热","type":1},{"host":{"a":"#取上级源码"},"ins":[],"ors":[{"a":"m","v":"[\"首页\",\"最新\",\"最热\",\"高清\",\"互动\",\"收藏\",\"十分钟+\"]"}],"sign":"Tab","type":8},{"attr":"{\"btNext\":false,\"desc\":false,\"flow\":true,\"itemtarget\":\"#播放器\",\"max\":0,\"row\":2,\"type\":5}","host":{"a":"#爬虫","v":"{\"cookie\":\"language\\u003dcn_CN\",\"mode\":0,\"pn_raise\":1,\"pn_start\":1,\"ua\":\"#PC\",\"url\":\"http://old.workgreat11.live/v.php?category\\u003d收藏\\u0026viewtype\\u003dbasic\\u0026page\\u003d#PN#\"}"},"ins":[{"a":"list","s":[{"a":"list","v":".get(.listchannel)"},{"a":"name","v":".get(a img).a(title)"},{"a":"url","v":".get(a).a(href)"},{"a":"img","v":".get(a img).a(src)"},{"a":"msg","v":".c(时长:).get(div.listchannel).ty(时长:\u003c/span\u003e).tz(\u003cspan class\u003d\"info\"\u003e添加时间:\u003c/span\u003e).t().c(时间:).get(div.listchannel).ty(添加时间:\u003c/span\u003e).tz(\u003cspan class\u003d\"info\"\u003e作者:\u003c/span\u003e).t()"},{"a":"prev"},{"a":"next"},{"a":"tail"}]}],"ors":[{"a":"screen","v":"收藏+本月收藏\u003drf+最多收藏\u003dmf"}],"sign":"收藏","type":1},{"attr":"{\"btNext\":false,\"desc\":false,\"flow\":true,\"itemtarget\":\"#播放器\",\"max\":0,\"row\":2,\"type\":5}","host":{"a":"#爬虫","v":"{\"cookie\":\"language\\u003dcn_CN\",\"mode\":0,\"pn_raise\":1,\"pn_start\":1,\"ua\":\"#PC\",\"url\":\"http://old.workgreat11.live/index.php\"}"},"ins":[{"a":"list","s":[{"a":"list","v":".get(#tab-featured p)"},{"a":"name","v":".get(span.title).t()"},{"a":"url","v":".get(a).a(href)"},{"a":"img","v":".get(img.moduleFeaturedThumb).a(src)"},{"a":"msg","v":".c(时长:).get(span.duration).t().c(-时间:).get(p).ty(:\u003c/span\u003e).tz(by).t()"},{"a":"prev"},{"a":"next"},{"a":"tail"}]}],"sign":"首页","type":1},{"attr":"{\"btNext\":false,\"desc\":false,\"flow\":true,\"itemtarget\":\"#播放器\",\"max\":0,\"row\":2,\"type\":5}","host":{"a":"#爬虫","v":"{\"cookie\":\"language\\u003dcn_CN\",\"mode\":0,\"pn_raise\":1,\"pn_start\":1,\"ua\":\"#PC\",\"url\":\"http://old.workgreat11.live/v.php?next\\u003dwatch\\u0026page\\u003d#PN#\"}"},"ins":[{"a":"list","s":[{"a":"list","v":".get(.listchannel)"},{"a":"name","v":".get(a img).a(title)"},{"a":"url","v":".get(a).a(href)"},{"a":"img","v":".get(a img).a(src)"},{"a":"msg","v":".c(时长:).get(div.listchannel).ty(时长:\u003c/span\u003e).tz(\u003cspan class\u003d\"info\"\u003e添加时间:\u003c/span\u003e).t().c(时间:).get(div.listchannel).ty(添加时间:\u003c/span\u003e).tz(\u003cspan class\u003d\"info\"\u003e作者:\u003c/span\u003e).t()"},{"a":"prev"},{"a":"next"},{"a":"tail"}]}],"sign":"最新","type":1},{"attr":"{\"btNext\":false,\"desc\":false,\"flow\":true,\"itemtarget\":\"#播放器\",\"max\":0,\"row\":2,\"type\":5}","host":{"a":"#爬虫","v":"{\"cookie\":\"language\\u003dcn_CN\",\"mode\":0,\"pn_raise\":1,\"pn_start\":1,\"ua\":\"#PC\",\"url\":\"http://old.workgreat11.live/v.php?category\\u003dhd\\u0026viewtype\\u003dbasic\\u0026page\\u003d#PN#\"}"},"ins":[{"a":"list","s":[{"a":"list","v":".get(.listchannel)"},{"a":"name","v":".get(a img).a(title)"},{"a":"url","v":".get(a).a(href)"},{"a":"img","v":".get(a img).a(src)"},{"a":"msg","v":".c(时长:).get(div.listchannel).ty(时长:\u003c/span\u003e).tz(\u003cspan class\u003d\"info\"\u003e添加时间:\u003c/span\u003e).t().c(时间:).get(div.listchannel).ty(添加时间:\u003c/span\u003e).tz(\u003cspan class\u003d\"info\"\u003e作者:\u003c/span\u003e).t()"},{"a":"prev"},{"a":"next"},{"a":"tail"}]}],"sign":"高清","type":1},{"attr":"{\"btNext\":false,\"desc\":false,\"flow\":true,\"itemtarget\":\"#播放器\",\"max\":0,\"row\":2,\"type\":5}","host":{"a":"#爬虫","v":"{\"cookie\":\"language\\u003dcn_CN\",\"mode\":0,\"pn_raise\":1,\"pn_start\":1,\"ua\":\"#PC\",\"url\":\"http://old.workgreat11.live/v.php?category\\u003d互动\\u0026viewtype\\u003dbasic\\u0026page\\u003d#PN#\"}"},"ins":[{"a":"list","s":[{"a":"list","v":".get(.listchannel)"},{"a":"name","v":".get(a img).a(title)"},{"a":"url","v":".get(a).a(href)"},{"a":"img","v":".get(a img).a(src)"},{"a":"msg","v":".c(时长:).get(div.listchannel).ty(时长:\u003c/span\u003e).tz(\u003cspan class\u003d\"info\"\u003e添加时间:\u003c/span\u003e).t().c(时间:).get(div.listchannel).ty(添加时间:\u003c/span\u003e).tz(\u003cspan class\u003d\"info\"\u003e作者:\u003c/span\u003e).t()"},{"a":"prev"},{"a":"next"},{"a":"tail"}]}],"ors":[{"a":"screen","v":"互动+最近得分\u003drp+最近加精\u003drf+本月讨论\u003dmd"}],"sign":"互动","type":1},{"attr":"{\"btNext\":false,\"desc\":false,\"flow\":true,\"itemtarget\":\"#播放器\",\"max\":0,\"row\":2,\"type\":5}","host":{"a":"#爬虫","v":"{\"cookie\":\"language\\u003dcn_CN\",\"mode\":0,\"pn_raise\":1,\"pn_start\":1,\"ua\":\"#PC\",\"url\":\"http://old.workgreat11.live/v.php?category\\u003dlong\\u0026viewtype\\u003dbasic\\u0026page\\u003d#PN#\"}"},"ins":[{"a":"list","s":[{"a":"list","v":".get(.listchannel)"},{"a":"name","v":".get(a img).a(title)"},{"a":"url","v":".get(a).a(href)"},{"a":"img","v":".get(a img).a(src)"},{"a":"msg","v":".c(时长:).get(div.listchannel).ty(时长:\u003c/span\u003e).tz(\u003cspan class\u003d\"info\"\u003e添加时间:\u003c/span\u003e).t().c(时间:).get(div.listchannel).ty(添加时间:\u003c/span\u003e).tz(\u003cspan class\u003d\"info\"\u003e作者:\u003c/span\u003e).t()"},{"a":"prev"},{"a":"next"},{"a":"tail"}]}],"sign":"十分钟+","type":1}],"name":"91Porn","sign":"04efcf3568db06d1e590356056d83840","sqlId":0,"vars":[],"version":0}