{"baseUrl":false,"coreVersion":8,"ine":"搜索","inq":"TAB","ins":[],"mous":[{"attr":"{\"bxt\":false}","host":{"a":"#UOkHttp","v":""},"ins":[{"a":"sort","s":[{"a":"sort","v":".json(data).json(vod_play_list).z(\"player_name_zh\".*?\"son\":\\[.*?\\])"},{"a":"s_name","v":".z2(\"player_info\":\"\\(.*?\\)\")"},{"a":"list","v":".z2(\"son\":\\[\\(.*?\\)\\]).z(\\{.*?\\})"},{"a":"name","v":".json(title)"},{"a":"url","v":".c(http://js.voooe.cn/1787799317json-99/?wap\u003d1\u0026url\u003d).json(url)"}]},{"a":"info","s":[{"a":"info","v":".json(data).json(vod_content)"}]},{"a":"con","s":[{"a":"playurl_regex","v":""},{"a":"putjs","v":"var data \u003d document.body.innerHTML;\nvar dizhi \u003d data.match(/\"url\":\"(.*?)\"/)[1];\nurl \u003d dizhi.replace(/\\\\/g, \u0027\u0027);\nurl \u003d url.replace(\u0027\u0026amp;\u0027, \u0027\u0026\u0027);\nvar iframe \u003d document.createElement(\u0027video\u0027);\niframe.src \u003d url;\ndocument.write(iframe);"}]}],"sign":"播放器","type":22},{"attr":"{\"btNext\":false,\"desc\":false,\"flow\":false,\"imgHeader\":\"80\",\"imgHeight\":0,\"itemtarget\":\"播放器\",\"max\":0,\"row\":3,\"type\":5}","host":{"a":"#爬虫","v":"{\"code\":\"\",\"head\":\"\",\"mode\":1,\"pn_raise\":1,\"pn_start\":1,\"post\":\"\",\"ua\":\"Mozilla/5.0 (Windows NT 10.0; Win64; x64) AppleWebKit/537.36 (KHTML, like Gecko) dgtv/1.0.0 Chrome/61.0.3163.100 Electron/2.0.18 Safari/537.36\",\"url\":\"http://dgdy.in/api.php?g\\u003dPC\\u0026m\\u003dcategory\\u0026a\\u003dfilter\\u0026cid\\u003d4\\u0026page\\u003d#PN#\\u0026limit\\u003d20\\u0026sort\\u003d排序\\u0026vod_ids\\u003d\\u0026vod_type\\u003d类型\\u0026vod_area\\u003d地区\\u0026vod_year\\u003d年份\"}"},"ins":[{"a":"list","s":[{"a":"list","v":".json(data).json(data)"},{"a":"name","v":".json(vod_name)"},{"a":"url","v":".c(http://dgdy.in/api.php?g\u003dPC\u0026m\u003dvod\u0026a\u003dshow\u0026id\u003d).json(vod_id)"},{"a":"img","v":".json(vod_pic)"},{"a":"msg","v":".json(vod_type)"},{"a":"prev","v":""},{"a":"next","v":""},{"a":"tail","v":""}]}],"ors":[{"a":"screen","v":"类型+全部\u003d+真人\u003d真人+音乐\u003d音乐+旅行\u003d旅行+脱口\u003d脱口+美食\u003d美食+情感\u003d情感\n地区+全部\u003d+内地\u003d内地+美国\u003d美国+韩国\u003d韩国+日本\u003d日本+台湾\u003d台湾+香港\u003d香港+台湾\u003d台湾+其他\u003d其他\n年份+全部\u003d+2020\u003d2020+2019\u003d2019+2018\u003d2018+2017\u003d2017+2016\u003d2016+2015\u003d2015+2014\u003d2014+2013\u003d2013+2012\u003d2012+2011\u003d2011+2010\u003d2010+2009\u003d2009\n排序+最多点赞\u003d1+最多播放\u003d2+最近更新\u003d3"}],"sign":"综艺","type":1},{"attr":"{\"btNext\":false,\"desc\":false,\"flow\":false,\"imgHeader\":\"80\",\"imgHeight\":0,\"itemtarget\":\"播放器\",\"max\":0,\"row\":3,\"type\":5}","host":{"a":"#爬虫","v":"{\"code\":\"\",\"head\":\"\",\"mode\":1,\"pn_raise\":1,\"pn_start\":1,\"post\":\"\",\"ua\":\"Mozilla/5.0 (Windows NT 10.0; Win64; x64) AppleWebKit/537.36 (KHTML, like Gecko) dgtv/1.0.0 Chrome/61.0.3163.100 Electron/2.0.18 Safari/537.36\",\"url\":\"http://dgdy.in/api.php?g\\u003dPC\\u0026m\\u003dcategory\\u0026a\\u003dfilter\\u0026cid\\u003d1\\u0026page\\u003d#PN#\\u0026limit\\u003d20\\u0026sort\\u003d排序\\u0026vod_ids\\u003d\\u0026vod_type\\u003d类型\\u0026vod_area\\u003d地区\\u0026vod_year\\u003d年份\"}"},"ins":[{"a":"list","s":[{"a":"list","v":".json(data).json(data)"},{"a":"name","v":".json(vod_name)"},{"a":"url","v":".c(http://dgdy.in/api.php?g\u003dPC\u0026m\u003dvod\u0026a\u003dshow\u0026id\u003d).json(vod_id)"},{"a":"img","v":".json(vod_pic)"},{"a":"msg","v":".json(vod_type)"},{"a":"prev","v":""},{"a":"next","v":""},{"a":"tail","v":""}]}],"ors":[{"a":"screen","v":"类型+全部\u003d+动作\u003d动作+科幻\u003d科幻+喜剧\u003d喜剧+爱情\u003d爱情+动画\u003d动画+战争\u003d战争+恐怖\u003d恐怖+记录\u003d记录+灾难\u003d灾难+剧情\u003d剧情\n地区+全部\u003d+大陆\u003d大陆+韩国\u003d韩国+香港\u003d香港+台湾\u003d台湾+日本\u003d日本+美国\u003d美国+泰国\u003d泰国+英国\u003d英国+其他\u003d其他\n年份+全部\u003d+2020\u003d2020+2019\u003d2019+2018\u003d2018+2017\u003d2017+2016\u003d2016+2015\u003d2015+2014\u003d2014+2013\u003d2013+2012\u003d2012+2011\u003d2011+2010\u003d2010+2009前\u003d2009前\n排序+最多点赞\u003d1+最多播放\u003d2+最近更新\u003d3"}],"sign":"电影","type":1},{"host":{"a":"#爬虫","v":""},"ins":[],"ors":[{"a":"m","v":"[\"电影\",\"电视剧\",\"动漫\",\"综艺\"]"}],"sign":"TAB","type":8},{"attr":"{\"btNext\":false,\"desc\":false,\"flow\":false,\"imgHeader\":\"80\",\"imgHeight\":0,\"itemtarget\":\"播放器\",\"max\":0,\"row\":3,\"type\":5}","host":{"a":"#爬虫","v":"{\"code\":\"\",\"head\":\"\",\"mode\":1,\"pn_raise\":1,\"pn_start\":1,\"post\":\"\",\"ua\":\"Mozilla/5.0 (Windows NT 10.0; Win64; x64) AppleWebKit/537.36 (KHTML, like Gecko) dgtv/1.0.0 Chrome/61.0.3163.100 Electron/2.0.18 Safari/537.36\",\"url\":\"http://dgdy.in/api.php?g\\u003dPC\\u0026m\\u003dcategory\\u0026a\\u003dfilter\\u0026cid\\u003d3\\u0026page\\u003d#PN#\\u0026limit\\u003d20\\u0026sort\\u003d排序\\u0026vod_ids\\u003d\\u0026vod_type\\u003d类型\\u0026vod_area\\u003d地区\\u0026vod_year\\u003d年份\"}"},"ins":[{"a":"list","s":[{"a":"list","v":".json(data).json(data)"},{"a":"name","v":".json(vod_name)"},{"a":"url","v":".c(http://dgdy.in/api.php?g\u003dPC\u0026m\u003dvod\u0026a\u003dshow\u0026id\u003d).json(vod_id)"},{"a":"img","v":".json(vod_pic)"},{"a":"msg","v":".json(vod_type)"},{"a":"prev","v":""},{"a":"next","v":""},{"a":"tail","v":""}]}],"ors":[{"a":"screen","v":"类型+全部\u003d+动作\u003d动作+科幻\u003d科幻+热血\u003d热血+推理\u003d推理+喜剧\u003d喜剧+冒险\u003d冒险+剧情\u003d剧情+奇幻\u003d奇幻+悬疑\u003d悬疑\n地区+全部\u003d+大陆\u003d大陆+韩国\u003d韩国+香港\u003d香港+台湾\u003d台湾+日本\u003d日本+美国\u003d美国+法国\u003d法国+英国\u003d英国+德国\u003d德国+西班牙\u003d西班牙\n年份+全部\u003d+2020\u003d2020+2019\u003d2019+2018\u003d2018+2017\u003d2017+2016\u003d2016+2015\u003d2015+2014\u003d2014+2013\u003d2013+2012\u003d2012+2011\u003d2011+2010\u003d2010+2009\u003d2009\n排序+最多点赞\u003d1+最多播放\u003d2+最近更新\u003d3"}],"sign":"动漫","type":1},{"attr":"{\"btNext\":false,\"desc\":false,\"flow\":false,\"imgHeader\":\"80\",\"imgHeight\":0,\"itemtarget\":\"播放器\",\"max\":0,\"row\":0,\"type\":1}","host":{"a":"#爬虫","v":"{\"code\":\"\",\"head\":\"\",\"mode\":1,\"pn_raise\":1,\"pn_start\":1,\"post\":\"\",\"ua\":\"Mozilla/5.0 (Windows NT 10.0; Win64; x64) AppleWebKit/537.36 (KHTML, like Gecko) dgtv/1.0.0 Chrome/61.0.3163.100 Electron/2.0.18 Safari/537.36\",\"url\":\"http://dgdy.in/api.php?g\\u003dPC\\u0026m\\u003dpublic\\u0026a\\u003dsearch\\u0026page\\u003d1\\u0026limit\\u003d20\\u0026keyword\\u003d#KEY#\"}"},"ins":[{"a":"list","s":[{"a":"list","v":".json(data).json(data)"},{"a":"name","v":".json(vod_name)"},{"a":"url","v":".c(http://dgdy.in/api.php?g\u003dPC\u0026m\u003dvod\u0026a\u003dshow\u0026id\u003d).json(vod_id)"},{"a":"img","v":".json(vod_pic)"},{"a":"msg","v":".json(vod_content)"},{"a":"prev","v":""},{"a":"next","v":""},{"a":"tail","v":""}]}],"sign":"搜索","type":1},{"attr":"{\"btNext\":false,\"desc\":false,\"flow\":false,\"imgHeader\":\"80\",\"imgHeight\":0,\"itemtarget\":\"播放器\",\"max\":0,\"row\":3,\"type\":5}","host":{"a":"#爬虫","v":"{\"code\":\"\",\"head\":\"\",\"mode\":1,\"pn_raise\":1,\"pn_start\":1,\"post\":\"\",\"ua\":\"Mozilla/5.0 (Windows NT 10.0; Win64; x64) AppleWebKit/537.36 (KHTML, like Gecko) dgtv/1.0.0 Chrome/61.0.3163.100 Electron/2.0.18 Safari/537.36\",\"url\":\"http://dgdy.in/api.php?g\\u003dPC\\u0026m\\u003dcategory\\u0026a\\u003dfilter\\u0026cid\\u003d2\\u0026page\\u003d#PN#\\u0026limit\\u003d20\\u0026sort\\u003d排序\\u0026vod_ids\\u003d\\u0026vod_type\\u003d类型\\u0026vod_area\\u003d地区\\u0026vod_year\\u003d年份\"}"},"ins":[{"a":"list","s":[{"a":"list","v":".json(data).json(data)"},{"a":"name","v":".json(vod_name)"},{"a":"url","v":".c(http://dgdy.in/api.php?g\u003dPC\u0026m\u003dvod\u0026a\u003dshow\u0026id\u003d).json(vod_id)"},{"a":"img","v":".json(vod_pic)"},{"a":"msg","v":".json(vod_type)"},{"a":"prev","v":""},{"a":"next","v":""},{"a":"tail","v":""}]}],"ors":[{"a":"screen","v":"类型+全部\u003d+古装\u003d古装+战争\u003d战争+青春偶像\u003d青春偶像+喜剧\u003d喜剧+家庭\u003d家庭+犯罪\u003d犯罪+动作\u003d动作+奇幻\u003d奇幻+剧情\u003d剧情+历史\u003d历史+经典\u003d经典+乡村\u003d乡村+情景\u003d情景+商战\u003d商战+网剧\u003d网剧+其他\u003d其他\n地区+全部\u003d+内地\u003d内地+美国\u003d美国+韩国\u003d韩国+日本\u003d日本+台湾\u003d台湾+香港\u003d香港+泰国\u003d泰国+其他\u003d其他\n年份+全部\u003d+2020\u003d2020+2019\u003d2019+2018\u003d2018+2017\u003d2017+2016\u003d2016+2015\u003d2015+2014\u003d2014+2013\u003d2013+2012\u003d2012+2011\u003d2011+2010\u003d2010+2009\u003d2009\n排序+最多点赞\u003d1+最多播放\u003d2+最近更新\u003d3"}],"sign":"电视剧","type":1}],"name":"冬瓜影视","sign":"414bb844a4e854743f92aee0105707b9","sqlId":0,"vars":[],"version":20210101}