{"baseUrl":true,"coreVersion":8,"ine":"","inq":"主页","ins":[],"mous":[{"attr":"{\"childmou\":\"主页数据\"}","host":{"a":"#爬虫","v":"{\"code\":\"\",\"head\":\"\",\"mode\":1,\"pn_raise\":1,\"pn_start\":1,\"post\":\"\",\"ua\":\"\",\"url\":\"http://halihali.li/\"}"},"ins":[{"a":"a","s":[{"a":"sort","v":".get(div.index-list-l)"},{"a":"s_name","v":".get(span).t()"}]}],"sign":"主页","type":5,"vars":[]},{"attr":"{\"btNext\":false,\"desc\":false,\"flow\":false,\"imgHeader\":\"80\",\"imgHeight\":0,\"itemtarget\":\"播放\",\"max\":0,\"row\":2,\"type\":9}","host":{"a":"#取上级源码","v":""},"ins":[{"a":"list","s":[{"a":"list","v":".get(li)"},{"a":"name","v":".get(p.name).t()"},{"a":"url","v":".c(http://t.mtyee.com/ne2/s).get(a.li-hv).a(href).z(\\d+).ct(.js)"},{"a":"img","v":".get(img).a(data-original)"},{"a":"msg","v":".get(p.bz).t()"},{"a":"author","v":""},{"a":"prev","v":""},{"a":"next","v":""},{"a":"tail","v":""}]}],"sign":"主页数据","type":1,"vars":[]},{"attr":"{\"bxt\":false}","host":{"a":"#读上级地址","v":""},"ins":[{"a":"sort","s":[{"a":"sort","v":".z(var lianzaijs.*?lianzaijs.*?_ed)"},{"a":"s_name","v":".z2(playarr.*?,\\(.*?\\),)"},{"a":"list","v":".z(\".*?\")"},{"a":"name","v":".z2(.*\\(,.*?\\)\").th(%u##\\u).th(,##{\"title\":\").ct(\"}).json(title)"},{"a":"url","v":".z2(\"\\(.*?\\),)"}]},{"a":"info","s":[{"a":"info","v":""}]},{"a":"con","s":[{"a":"playurl_regex","v":""},{"a":"putjs","v":""}]}],"sign":"播放","type":22,"vars":[]}],"name":"哈哩哈里","sign":"5d1c0e003926e9f8af943257c54bf68f","sqlId":0,"vars":[],"version":0}