{"baseUrl":true,"coreVersion":8,"inq":"主页","ins":[],"mous":[{"attr":"{\"btNext\":false,\"desc\":false,\"flow\":false,\"imgHeight\":0,\"itemtarget\":\"播放器\",\"max\":0,\"row\":3,\"type\":5}","host":{"a":"#爬虫","v":"{\"code\":\"\",\"head\":\"\",\"mode\":1,\"pn_raise\":1,\"pn_start\":1,\"post\":\"\",\"ua\":\"#PC\",\"url\":\"http://www.4f3f.com/htm/Video8/#PN#.htm\"}"},"ins":[{"a":"list","s":[{"a":"list","v":".get(ul#content li)"},{"a":"name","v":".get(a.video-pic.loading).a(title)"},{"a":"url","v":".get(a.video-pic.loading).a(href)"},{"a":"img","v":".get(a.video-pic.loading).a(data-original)"},{"a":"msg","v":".get(span.score).t()"},{"a":"prev"},{"a":"next"},{"a":"tail"}]}],"sign":"颜射吃精","type":1},{"attr":"{\"btNext\":false,\"desc\":false,\"flow\":false,\"imgHeight\":0,\"itemtarget\":\"播放器\",\"max\":0,\"row\":3,\"type\":5}","host":{"a":"#爬虫","v":"{\"code\":\"\",\"head\":\"\",\"mode\":1,\"pn_raise\":1,\"pn_start\":1,\"post\":\"\",\"ua\":\"#PC\",\"url\":\"http://www.4f3f.com/htm/Movie4/#PN#.htm\"}"},"ins":[{"a":"list","s":[{"a":"list","v":".get(ul#content li)"},{"a":"name","v":".get(a.video-pic.loading).a(title)"},{"a":"url","v":".get(a.video-pic.loading).a(href)"},{"a":"img","v":".get(a.video-pic.loading).a(data-original)"},{"a":"msg","v":".get(span.score).t()"},{"a":"prev"},{"a":"next"},{"a":"tail"}]}],"sign":"中文有码","type":1},{"attr":"{\"btNext\":false,\"desc\":false,\"flow\":false,\"imgHeight\":0,\"itemtarget\":\"播放器\",\"max\":0,\"row\":3,\"type\":5}","host":{"a":"#爬虫","v":"{\"code\":\"\",\"head\":\"\",\"mode\":1,\"pn_raise\":1,\"pn_start\":1,\"post\":\"\",\"ua\":\"#PC\",\"url\":\"http://www.4f3f.com/htm/Movie1/#PN#.htm\"}"},"ins":[{"a":"list","s":[{"a":"list","v":".get(ul#content li)"},{"a":"name","v":".get(a.video-pic.loading).a(title)"},{"a":"url","v":".get(a.video-pic.loading).a(href)"},{"a":"img","v":".get(a.video-pic.loading).a(data-original)"},{"a":"msg","v":".get(span.score).t()"},{"a":"prev"},{"a":"next"},{"a":"tail"}]}],"sign":"高清无码","type":1},{"attr":"{\"btNext\":false,\"desc\":false,\"flow\":false,\"imgHeight\":0,\"itemtarget\":\"播放器\",\"max\":0,\"row\":3,\"type\":5}","host":{"a":"#爬虫","v":"{\"code\":\"\",\"head\":\"\",\"mode\":1,\"pn_raise\":1,\"pn_start\":1,\"post\":\"\",\"ua\":\"#PC\",\"url\":\"http://www.4f3f.com/htm/Video6/#PN#.htm\"}"},"ins":[{"a":"list","s":[{"a":"list","v":".get(ul#content li)"},{"a":"name","v":".get(a.video-pic.loading).a(title)"},{"a":"url","v":".get(a.video-pic.loading).a(href)"},{"a":"img","v":".get(a.video-pic.loading).a(data-original)"},{"a":"msg","v":".get(span.score).t()"},{"a":"prev"},{"a":"next"},{"a":"tail"}]}],"sign":"网红主播","type":1},{"attr":"{\"btNext\":false,\"desc\":false,\"flow\":false,\"imgHeight\":0,\"itemtarget\":\"播放器\",\"max\":0,\"row\":3,\"type\":5}","host":{"a":"#爬虫","v":"{\"code\":\"\",\"head\":\"\",\"mode\":1,\"pn_raise\":1,\"pn_start\":1,\"post\":\"\",\"ua\":\"#PC\",\"url\":\"http://www.4f3f.com/htm/Movie7/#PN#.htm\"}"},"ins":[{"a":"list","s":[{"a":"list","v":".get(ul#content li)"},{"a":"name","v":".get(a.video-pic.loading).a(title)"},{"a":"url","v":".get(a.video-pic.loading).a(href)"},{"a":"img","v":".get(a.video-pic.loading).a(data-original)"},{"a":"msg","v":".get(span.score).t()"},{"a":"prev"},{"a":"next"},{"a":"tail"}]}],"sign":"经典三级","type":1},{"attr":"{\"btNext\":false,\"desc\":false,\"flow\":false,\"imgHeight\":0,\"itemtarget\":\"播放器\",\"max\":0,\"row\":3,\"type\":5}","host":{"a":"#爬虫","v":"{\"code\":\"\",\"head\":\"\",\"mode\":1,\"pn_raise\":1,\"pn_start\":1,\"post\":\"\",\"ua\":\"#PC\",\"url\":\"http://www.4f3f.com/htm/Movie2/#PN#.htm\"}"},"ins":[{"a":"list","s":[{"a":"list","v":".get(ul#content li)"},{"a":"name","v":".get(a.video-pic.loading).a(title)"},{"a":"url","v":".get(a.video-pic.loading).a(href)"},{"a":"img","v":".get(a.video-pic.loading).a(data-original)"},{"a":"msg","v":".get(span.score).t()"},{"a":"prev"},{"a":"next"},{"a":"tail"}]}],"sign":"高清有码","type":1},{"attr":"{\"btNext\":false,\"desc\":false,\"flow\":false,\"imgHeight\":0,\"itemtarget\":\"播放器\",\"max\":0,\"row\":3,\"type\":5}","host":{"a":"#爬虫","v":"{\"code\":\"\",\"head\":\"\",\"mode\":1,\"pn_raise\":1,\"pn_start\":1,\"post\":\"\",\"ua\":\"#PC\",\"url\":\"http://www.4f3f.com/htm/Movie3/#PN#.htm\"}"},"ins":[{"a":"list","s":[{"a":"list","v":".get(ul#content li)"},{"a":"name","v":".get(a.video-pic.loading).a(title)"},{"a":"url","v":".get(a.video-pic.loading).a(href)"},{"a":"img","v":".get(a.video-pic.loading).a(data-original)"},{"a":"msg","v":".get(span.score).t()"},{"a":"prev"},{"a":"next"},{"a":"tail"}]}],"sign":"中文无码","type":1},{"attr":"{\"btNext\":false,\"desc\":false,\"flow\":false,\"imgHeight\":0,\"itemtarget\":\"播放器\",\"max\":0,\"row\":3,\"type\":5}","host":{"a":"#爬虫","v":"{\"code\":\"\",\"head\":\"\",\"mode\":1,\"pn_raise\":1,\"pn_start\":1,\"post\":\"\",\"ua\":\"#PC\",\"url\":\"http://www.4f3f.com/htm/Video4/#PN#.htm\"}"},"ins":[{"a":"list","s":[{"a":"list","v":".get(ul#content li)"},{"a":"name","v":".get(a.video-pic.loading).a(title)"},{"a":"url","v":".get(a.video-pic.loading).a(href)"},{"a":"img","v":".get(a.video-pic.loading).a(data-original)"},{"a":"msg","v":".get(span.score).t()"},{"a":"prev"},{"a":"next"},{"a":"tail"}]}],"sign":"成人动漫","type":1},{"attr":"{\"btNext\":false,\"desc\":false,\"flow\":false,\"imgHeight\":0,\"itemtarget\":\"播放器\",\"max\":0,\"row\":3,\"type\":5}","host":{"a":"#爬虫","v":"{\"code\":\"\",\"head\":\"\",\"mode\":1,\"pn_raise\":1,\"pn_start\":1,\"post\":\"\",\"ua\":\"#PC\",\"url\":\"http://www.4f3f.com/htm/Movie5/#PN#.htm\"}"},"ins":[{"a":"list","s":[{"a":"list","v":".get(ul#content li)"},{"a":"name","v":".get(a.video-pic.loading).a(title)"},{"a":"url","v":".get(a.video-pic.loading).a(href)"},{"a":"img","v":".get(a.video-pic.loading).a(data-original)"},{"a":"msg","v":".get(span.score).t()"},{"a":"prev"},{"a":"next"},{"a":"tail"}]}],"sign":"欧美无码","type":1},{"attr":"{\"btNext\":false,\"desc\":false,\"flow\":false,\"imgHeight\":0,\"itemtarget\":\"播放器\",\"max\":0,\"row\":3,\"type\":5}","host":{"a":"#爬虫","v":"{\"code\":\"\",\"head\":\"\",\"mode\":1,\"pn_raise\":1,\"pn_start\":1,\"post\":\"\",\"ua\":\"#PC\",\"url\":\"http://www.4f3f.com/htm/Movie6/#PN#.htm\"}"},"ins":[{"a":"list","s":[{"a":"list","v":".get(ul#content li)"},{"a":"name","v":".get(a.video-pic.loading).a(title)"},{"a":"url","v":".get(a.video-pic.loading).a(href)"},{"a":"img","v":".get(a.video-pic.loading).a(data-original)"},{"a":"msg","v":".get(span.score).t()"},{"a":"prev"},{"a":"next"},{"a":"tail"}]}],"sign":"韩国剧情","type":1},{"attr":"{\"btNext\":false,\"desc\":false,\"flow\":false,\"imgHeight\":0,\"itemtarget\":\"播放器\",\"max\":0,\"row\":3,\"type\":5}","host":{"a":"#爬虫","v":"{\"code\":\"\",\"head\":\"\",\"mode\":1,\"pn_raise\":1,\"pn_start\":1,\"post\":\"\",\"ua\":\"#PC\",\"url\":\"http://www.4f3f.com/htm/Video1/#PN#.htm\"}"},"ins":[{"a":"list","s":[{"a":"list","v":".get(ul#content li)"},{"a":"name","v":".get(a.video-pic.loading).a(title)"},{"a":"url","v":".get(a.video-pic.loading).a(href)"},{"a":"img","v":".get(a.video-pic.loading).a(data-original)"},{"a":"msg","v":".get(span.score).t()"},{"a":"prev"},{"a":"next"},{"a":"tail"}]}],"sign":"偷拍自拍","type":1},{"host":{"a":"#爬虫"},"ins":[],"ors":[{"a":"m","v":"[\"颜射吃精\",\"中文有码\",\"高清无码\",\"网红主播\",\"经典三级\",\"高清有码\",\"中文无码\",\"成人动漫\",\"欧美无码\",\"韩国剧情\",\"偷拍自拍\",\"欧美性爱\",\"日韩视频\",\"国产精选\",\"明星艳照\"]"}],"sign":"主页","type":8},{"attr":"{\"btNext\":false,\"desc\":false,\"flow\":false,\"imgHeight\":0,\"itemtarget\":\"播放器\",\"max\":0,\"row\":3,\"type\":5}","host":{"a":"#爬虫","v":"{\"code\":\"\",\"head\":\"\",\"mode\":1,\"pn_raise\":1,\"pn_start\":1,\"post\":\"\",\"ua\":\"#PC\",\"url\":\"http://www.4f3f.com/htm/Video3/#PN#.htm\"}"},"ins":[{"a":"list","s":[{"a":"list","v":".get(ul#content li)"},{"a":"name","v":".get(a.video-pic.loading).a(title)"},{"a":"url","v":".get(a.video-pic.loading).a(href)"},{"a":"img","v":".get(a.video-pic.loading).a(data-original)"},{"a":"msg","v":".get(span.score).t()"},{"a":"prev"},{"a":"next"},{"a":"tail"}]}],"sign":"欧美性爱","type":1},{"attr":"{\"bxt\":false}","host":{"a":"#读上级地址"},"ins":[{"a":"sort","s":[{"a":"sort","v":""},{"a":"s_name","v":""},{"a":"list","v":".get(div.play-list a)"},{"a":"name","v":".get(a).a(title)"},{"a":"url","v":".get(a).a(href)"}]},{"a":"info","s":[{"a":"info"}]},{"a":"con","s":[{"a":"playurl_regex"},{"a":"putjs"}]}],"sign":"播放器","type":22},{"attr":"{\"btNext\":false,\"desc\":false,\"flow\":false,\"imgHeight\":0,\"itemtarget\":\"播放器\",\"max\":0,\"row\":3,\"type\":5}","host":{"a":"#爬虫","v":"{\"code\":\"\",\"head\":\"\",\"mode\":1,\"pn_raise\":1,\"pn_start\":1,\"post\":\"\",\"ua\":\"#PC\",\"url\":\"http://www.4f3f.com/htm/Video2/#PN#.htm\"}"},"ins":[{"a":"list","s":[{"a":"list","v":".get(ul#content li)"},{"a":"name","v":".get(a.video-pic.loading).a(title)"},{"a":"url","v":".get(a.video-pic.loading).a(href)"},{"a":"img","v":".get(a.video-pic.loading).a(data-original)"},{"a":"msg","v":".get(span.score).t()"},{"a":"prev"},{"a":"next"},{"a":"tail"}]}],"sign":"日韩视频","type":1},{"attr":"{\"btNext\":false,\"desc\":false,\"flow\":false,\"imgHeight\":0,\"itemtarget\":\"播放器\",\"max\":0,\"row\":3,\"type\":5}","host":{"a":"#爬虫","v":"{\"code\":\"\",\"head\":\"\",\"mode\":1,\"pn_raise\":1,\"pn_start\":1,\"post\":\"\",\"ua\":\"#PC\",\"url\":\"http://www.4f3f.com/htm/Movie9/#PN#.htm\"}"},"ins":[{"a":"list","s":[{"a":"list","v":".get(ul#content li)"},{"a":"name","v":".get(a.video-pic.loading).a(title)"},{"a":"url","v":".get(a.video-pic.loading).a(href)"},{"a":"img","v":".get(a.video-pic.loading).a(data-original)"},{"a":"msg","v":".get(span.score).t()"},{"a":"prev"},{"a":"next"},{"a":"tail"}]}],"sign":"国产精选","type":1},{"attr":"{\"btNext\":false,\"desc\":false,\"flow\":false,\"imgHeight\":0,\"itemtarget\":\"播放器\",\"max\":0,\"row\":3,\"type\":5}","host":{"a":"#爬虫","v":"{\"code\":\"\",\"head\":\"\",\"mode\":1,\"pn_raise\":1,\"pn_start\":1,\"post\":\"\",\"ua\":\"#PC\",\"url\":\"http://www.4f3f.com/htm/Video5/#PN#.htm\"}"},"ins":[{"a":"list","s":[{"a":"list","v":".get(ul#content li)"},{"a":"name","v":".get(a.video-pic.loading).a(title)"},{"a":"url","v":".get(a.video-pic.loading).a(href)"},{"a":"img","v":".get(a.video-pic.loading).a(data-original)"},{"a":"msg","v":".get(span.score).t()"},{"a":"prev"},{"a":"next"},{"a":"tail"}]}],"sign":"明星艳照","type":1}],"name":"大香蕉","sign":"0b4916afc8914c1884282d88e231db26","sqlId":0,"vars":[],"version":0}