{"baseUrl":true,"coreVersion":8,"inq":"首页","ins":[],"mous":[{"attr":"{\"btNext\":false,\"desc\":false,\"flow\":false,\"imgHeight\":255,\"itemtarget\":\"内容垂直\",\"max\":0,\"row\":2,\"type\":5}","host":{"a":"#取上级源码","v":""},"ins":[{"a":"list","s":[{"a":"list","v":".get(article.excerpt.excerpt-c4)"},{"a":"name","v":".get(h2).t()"},{"a":"url","v":".c(https://smtmm.win).get(a.thumbnail).a(href)"},{"a":"img","v":".c(https://smtmm.win).get(.imgbox).a(style).z2(url[\\(]\\(.*?\\)[\\)])"},{"a":"msg","v":".get(time).t()"},{"a":"prev","v":""},{"a":"next","v":""},{"a":"tail","v":""}]}],"sign":"内容推荐列表","type":1},{"attr":"{\"btNext\":false,\"desc\":false,\"flow\":false,\"imgHeight\":0,\"itemtarget\":\"通用列表\",\"max\":0,\"row\":3,\"type\":8}","host":{"a":"#爬虫","v":"{\"code\":\"\",\"head\":\"\",\"mode\":1,\"pn_raise\":1,\"pn_start\":1,\"post\":\"\",\"ua\":\"\",\"url\":\"https://smtmm.win/\"}"},"ins":[{"a":"list","s":[{"a":"list","v":".get(div.sitenav \u003e ul \u003e li)"},{"a":"name","v":".get(a).t()"},{"a":"url","v":".get(a).a(href)"},{"a":"prev","v":""},{"a":"next","v":""},{"a":"tail","v":""}]}],"sign":"导航","type":1},{"host":{"a":"#爬虫","v":""},"ins":[],"ors":[{"a":"m","v":"[\"内容大图\",\"内容标签\",\"内容推荐\"]"}],"sign":"内容垂直","type":23},{"attr":"{\"itemtarget\":\"通用列表\"}","host":{"a":"#读上级地址","v":""},"ins":[{"a":"a","s":[{"a":"sort","v":".get(div.article-tags)"},{"a":"s_name","v":"标签"},{"a":"list","v":".get(a)"},{"a":"name","v":".get(a).t()"},{"a":"url","v":".get(a).a(href)"}]}],"sign":"内容标签","type":24},{"attr":"{\"btNext\":false,\"desc\":false,\"flow\":false,\"imgHeight\":560,\"itemtarget\":\"图片阅读器\",\"max\":0,\"row\":0,\"type\":5}","host":{"a":"#读上级地址","v":""},"ins":[{"a":"list","s":[{"a":"list","v":".get(article.article-content p).i(0)"},{"a":"name","v":".get(img).a(alt)"},{"a":"url","v":".var(url)"},{"a":"img","v":".get(img).a(data-original)"},{"a":"msg","v":""},{"a":"prev","v":""},{"a":"next","v":""},{"a":"tail","v":""}]}],"sign":"内容大图","type":1},{"attr":"{\"btNext\":false,\"desc\":false,\"flow\":true,\"headMou\":\"导航\",\"imgHeight\":0,\"itemtarget\":\"内容垂直\",\"max\":0,\"row\":2,\"type\":5}","host":{"a":"#爬虫","v":"{\"code\":\"\",\"head\":\"\",\"mode\":1,\"pn_raise\":1,\"pn_start\":1,\"post\":\"\",\"ua\":\"\",\"url\":\"https://smtmm.win/\"}"},"ins":[{"a":"list","s":[{"a":"list","v":".get(article.excerpt.excerpt-c5)"},{"a":"name","v":".get(h2).t()"},{"a":"url","v":".get(a.thumbnail).a(href)"},{"a":"img","v":".get(.imgbox).a(style).z2(url[\\(]\\(.*?\\)[\\)])"},{"a":"msg","v":".get(time).t()"},{"a":"prev","v":""},{"a":"next","v":".get(li.next-page a).a(href).th(?##/?)"},{"a":"tail","v":""}]}],"sign":"首页","type":1},{"attr":"{\"btNext\":false,\"desc\":false,\"flow\":true,\"imgHeight\":0,\"itemtarget\":\"内容垂直\",\"max\":0,\"row\":2,\"type\":5}","host":{"a":"#读上级地址","v":""},"ins":[{"a":"list","s":[{"a":"list","v":".get(article.excerpt.excerpt-c5)"},{"a":"name","v":".get(h2).t()"},{"a":"url","v":".get(a.thumbnail).a(href)"},{"a":"img","v":".get(.imgbox).a(style).z2(url[\\(]\\(.*?\\)[\\)])"},{"a":"msg","v":".get(time).t()"},{"a":"prev","v":""},{"a":"next","v":".get(li.next-page a).a(href).th(?##/?)"},{"a":"tail","v":""}]}],"sign":"通用列表","type":1},{"attr":"{\"btNext\":false,\"desc\":false,\"flow\":true,\"imgHeight\":0,\"itemtarget\":\"#图片\",\"max\":0,\"row\":0,\"type\":5}","host":{"a":"#读上级地址","v":""},"ins":[{"a":"list","s":[{"a":"list","v":".get(article.article-content \u003e p)"},{"a":"name","v":""},{"a":"url","v":".get(img).a(data-original)"},{"a":"img","v":".get(img).a(data-original)"},{"a":"msg","v":".get(img).a(alt)"},{"a":"prev","v":""},{"a":"next","v":""},{"a":"tail","v":""}]}],"sign":"图片阅读器","type":1},{"attr":"{\"childmou\":\"内容推荐列表\"}","host":{"a":"#读上级地址","v":""},"ins":[{"a":"a","s":[{"a":"sort","v":".get(div.excerpts)"},{"a":"s_name","v":"相关推荐"}]}],"sign":"内容推荐","type":5}],"name":"水蜜桃","sign":"8a2f6c7c3e75d8896699cc38f6e1a826","sqlId":0,"vars":[],"version":0}